{
  "id": "project-LICHEN-3gqi",
  "title": "Complete Simulation Infrastructure Enhancement Epic",
  "description": "Complete Simulation Infrastructure Enhancement Epic - Epic to track all enhancements to LICHEN simulation infrastructure including debugging capabilities, validation tests, and documentation for distributed testing without hardware requirements. This epic encompasses all the foundational work needed to validate the heterogeneous mesh network approach before requiring actual hardware deployment.",
  "status": "in_progress",
  "priority": 1,
  "issue_type": "epic",
  "assignee": "ec2-user",
  "owner": "me@mark.atwood.name",
  "created_at": "2026-07-15T03:18:15.665267Z",
  "created_by": "Mark Atwood",
  "updated_at": "2026-07-22T14:25:30.50846559Z",
  "started_at": "2026-07-22T14:25:30.50846559Z",
  "lease_expires_at": "2026-07-22T14:30:30.50846559Z",
  "heartbeat_at": "2026-07-22T14:25:30.50846559Z"
}
