{
  "id": "project-LICHEN-jmk8",
  "title": "[merge-conflict] worktree-worker23: xiao_s3_wio_sx1262.conf",
  "notes": "Commit: 41c7c46d6",
  "status": "closed",
  "priority": 1,
  "issue_type": "bug",
  "assignee": "AI Agent",
  "owner": "agent@lichen-project.dev",
  "created_at": "2026-07-23T00:33:49.475600662Z",
  "created_by": "AI Agent",
  "updated_at": "2026-07-23T01:52:25.275567069Z",
  "started_at": "2026-07-23T01:51:10.722887813Z",
  "closed_at": "2026-07-23T01:52:25.275567069Z",
  "close_reason": "Merge conflict resolved by standardizing retired board config comment across worktrees"
}
