{
  "id": "project-LICHEN-t2hn.7.2.2",
  "title": "Cover MeshCore ingress through gateway message contract",
  "description": "Reviews for project-LICHEN-t2hn.7.2 noted Meshtastic gateway tests now exercise the production message_contract submit_text sink, but MeshCore gateway tests still inject a custom submit sink. Add no-hardware MeshCore gateway coverage that initializes/pops the gateway message contract queue for submit_text ingress.",
  "status": "open",
  "priority": 3,
  "issue_type": "task",
  "owner": "me@mark.atwood.name",
  "created_at": "2026-07-01T18:23:16.188355Z",
  "created_by": "Mark Atwood",
  "updated_at": "2026-07-01T18:23:16.18887Z",
  "labels": [
    "zephyr",
    "meshcore",
    "testing",
    "app-interface",
    "meshtastic",
    "messaging",
    "firmware"
  ],
  "dependencies": [
    {
      "issue_id": "project-LICHEN-t2hn.7.2.2",
      "depends_on_id": "project-LICHEN-t2hn.7.2",
      "type": "parent-child",
      "created_at": "2026-07-01T18:23:16.18887Z"
    }
  ]
}
