{
  "id": "project-LICHEN-rilw",
  "title": "[CODEREVIEW-P2] ccp16.json not referenced in schema.json or spec appendix fully",
  "description": "test/vectors/schema.json and spec/02a-coordinated-capacity.md - New vector file requires schema update for fields like expected_channel. Also update Implementation Status. Pass 2 after code chunk. tagged codereview",
  "status": "in_progress",
  "priority": 2,
  "issue_type": "task",
  "assignee": "ec2-user",
  "created_at": "2026-07-22T17:02:51.838655858Z",
  "created_by": "ec2-user",
  "updated_at": "2026-07-22T17:03:34.550536802Z",
  "started_at": "2026-07-22T17:03:34.550536802Z",
  "lease_expires_at": "2026-07-22T17:08:34.550536802Z",
  "heartbeat_at": "2026-07-22T17:03:34.550536802Z",
  "labels": [
    "codereview"
  ]
}
