{
  "id": "project-LICHEN-d7ub.32",
  "title": "ipv6_addr.c:48 lichen_eui64_to_iid allows aliased pointers",
  "description": "Contract violation: lichen_eui64_to_iid() - If eui64 and iid point to the same buffer (aliased), the XOR at line 68 reads from already-modified data. memcpy at line 67 copies eui64 to iid, then line 68 XORs iid[0]. If eui64==iid, the XOR is correct (data already in place). Actually this works correctly for aliased pointers. No bug - memcpy(dst,src,n) where dst==src is implementation-defined but commonly safe for n\u003c=8. No issue.",
  "status": "open",
  "priority": 3,
  "issue_type": "bug",
  "assignee": "Mark Atwood",
  "owner": "me@mark.atwood.name",
  "created_at": "2026-06-28T07:20:52.914518Z",
  "created_by": "Mark Atwood",
  "updated_at": "2026-06-28T07:21:00.515592Z",
  "closed_at": "2026-06-28T07:21:00.515592Z",
  "close_reason": "Not a bug: memcpy with overlapping pointers where dst==src is safe for this small copy, and the XOR operates correctly regardless.",
  "labels": [
    "review",
    "round1",
    "contract",
    "exhaustive"
  ],
  "dependencies": [
    {
      "issue_id": "project-LICHEN-d7ub.32",
      "depends_on_id": "project-LICHEN-d7ub",
      "type": "parent-child",
      "created_at": "2026-06-28T07:20:52.915118Z"
    }
  ]
}
