{
  "id": "project-LICHEN-9c4y.22",
  "title": "Add MeshCore direct peer text prefix mapping",
  "description": "Follow-up from project-LICHEN-9c4y.12 support-matrix review. Current SEND_TXT_MSG direct-peer path validates the 6-byte MeshCore peer prefix and UTF-8 but returns ERR_NOT_FOUND because no prefix-to-LICHEN-peer mapping exists. Define and implement a compatibility-local mapping from MeshCore peer prefixes to LICHEN app-interface peers, add deterministic no-match/collision behavior, canonical vectors, and native_sim gateway/adapter tests before documenting direct peer text as supported.",
  "status": "in_progress",
  "priority": 3,
  "issue_type": "task",
  "assignee": "Mark Atwood",
  "owner": "me@mark.atwood.name",
  "created_at": "2026-07-02T01:05:25.187901Z",
  "created_by": "Mark Atwood",
  "updated_at": "2026-07-02T18:30:19.891085Z",
  "labels": [
    "zephyr",
    "meshcore",
    "messaging",
    "app-interface",
    "tests",
    "firmware"
  ],
  "dependencies": [
    {
      "issue_id": "project-LICHEN-9c4y.22",
      "depends_on_id": "project-LICHEN-9c4y",
      "type": "parent-child",
      "created_at": "2026-07-02T01:05:25.188457Z"
    }
  ]
}
