{
  "id": "project-LICHEN-34lx",
  "title": "[epic] Heltec WiFi LoRa 32 V3 support",
  "description": "Full support for Heltec WiFi LoRa 32 V3 (ESP32-S3 + SX1262, 915MHz). Board definitions exist at lichen/boards/heltec/heltec_wifi_lora32_v3/. Need validation in both simulation and real hardware. User has N30 version with 1100mAh battery.",
  "labels": ["defer-external"],
  "status": "open",
  "priority": 2,
  "issue_type": "epic",
  "assignee": "AI Agent",
  "owner": "me@mark.atwood.name",
  "created_at": "2026-07-10T22:17:12.410676Z",
  "created_by": "Mark Atwood",
  "updated_at": "2026-07-22T20:26:31.618244759Z",
  "started_at": "2026-07-22T20:26:31.618244759Z",
  "lease_expires_at": "2026-07-22T20:31:31.618244759Z",
  "heartbeat_at": "2026-07-22T20:26:31.618244759Z"
}
