{
  "id": "project-LICHEN-i1gk.105",
  "title": "[main.c:132-134] ret variable overwritten by LED operations before USB error path",
  "description": "Final pass: This was missed because the existing finding about ret initialization focused on the unrelated code path, not the specific LED interaction.\n\nRoot cause: At lines 132-147:\n  int main(void) {\n      int ret = 0;\n      ...\n      #if defined(HAS_LED)\n      if (gpio_is_ready_dt(\u0026led)) {\n          ret = gpio_pin_configure_dt(\u0026led, GPIO_OUTPUT_ACTIVE);  // line 141\n          if (ret \u003c 0) {\n              LOG_ERR(...);\n          } else {\n              led_configured = true;\n              led_set(1);\n          }\n      }\n      #endif\n      #if defined(CONFIG_USB_DEVICE_STACK)\n      ret = usb_enable(NULL);  // line 152\n\nThe variable 'ret' is reused between LED initialization and USB initialization. If gpio_pin_configure_dt fails (ret \u003c 0), the error is logged but ret is not reset. However, this doesn't actually affect the USB path because ret is immediately overwritten by usb_enable().\n\nActually, this is fine - ret is overwritten before use. Let me look for a real bug.",
  "status": "open",
  "priority": 4,
  "issue_type": "bug",
  "assignee": "Mark Atwood",
  "owner": "me@mark.atwood.name",
  "created_at": "2026-06-28T03:17:30.76667Z",
  "created_by": "Mark Atwood",
  "updated_at": "2026-06-28T03:17:34.308511Z",
  "closed_at": "2026-06-28T03:17:34.308511Z",
  "close_reason": "Invalid - ret is properly overwritten by usb_enable before use",
  "labels": [
    "review",
    "round4",
    "exhaustive"
  ],
  "dependencies": [
    {
      "issue_id": "project-LICHEN-i1gk.105",
      "depends_on_id": "project-LICHEN-i1gk",
      "type": "parent-child",
      "created_at": "2026-06-28T03:17:30.767171Z"
    }
  ]
}
