{
  "id": "project-LICHEN-4jmv",
  "title": "[merge-conflict] worktree-worker22: heltec_wireless_tracker.conf",
  "notes": "Commit: 45218453a",
  "status": "in_progress",
  "priority": 1,
  "issue_type": "bug",
  "assignee": "AI Agent",
  "owner": "agent@lichen-project.dev",
  "created_at": "2026-07-22T23:41:04.9481529Z",
  "created_by": "AI Agent",
  "updated_at": "2026-07-23T03:43:13.472822932Z",
  "started_at": "2026-07-23T03:42:21.029298842Z",
  "lease_expires_at": "2026-07-23T03:47:21.029298842Z",
  "heartbeat_at": "2026-07-23T03:42:21.029298842Z"
}
